karto_scanmatcher.cpython-312-aarch64-linux-gnu.so
karto_scanmatcher-1.0.0.dist-info/RECORD
karto_scanmatcher-1.0.0.dist-info/WHEEL
karto_scanmatcher-1.0.0.dist-info/top_level.txt
karto_scanmatcher-1.0.0.dist-info/METADATA
karto_scanmatcher-1.0.0.dist-info/licenses/LICENSE
