Metadata-Version: 2.1
Name: karto-scanmatcher
Version: 1.0.0
Summary: The Scan Matcher from OpenKarto with python bindings
Author: Jariullah Safi
Author-email: safijari@isu.edu
License-File: LICENSE
